linenotify/__init__.py
linenotify/exceptions.py
linenotify/service.py
linenotify/status.py
linenotify/validations.py
linenotify_python-0.1.1.dist-info/WHEEL
linenotify_python-0.1.1.dist-info/METADATA
linenotify_python-0.1.1.dist-info/RECORD
