Metadata-Version: 2.1
Name: linenotify-python
Version: 0.1.1
Summary: LINE notify Web API wrapper
Home-page: https://github.com/mukai1011/linenotify-python
License: MIT
Author: Koutaro Mukai
Author-email: mukai.k1011k@outlook.jp
Requires-Python: >=3.7,<3.11
Classifier: License :: OSI Approved :: MIT License
Classifier: Programming Language :: Python :: 3
Classifier: Programming Language :: Python :: 3.7
Classifier: Programming Language :: Python :: 3.8
Classifier: Programming Language :: Python :: 3.9
Classifier: Programming Language :: Python :: 3.10
Requires-Dist: Pillow (>=9.3.0,<10.0.0)
Requires-Dist: opencv-python (>=4.6.0.66,<5.0.0.0)
Requires-Dist: pydantic (>=1.10.2,<2.0.0)
Requires-Dist: requests (>=2.28.1,<3.0.0)
Project-URL: Repository, https://github.com/mukai1011/linenotify-python
